Metadata-Version: 1.0
Name: umOpener
Version: 0.0.9
Summary: netcdf4/GeoTiff/ENVI/grib(only read) read and wirte
Home-page: https://github.com/XiaoXiaowukong/opener
Author: neo
Author-email: james_neo@163.com
License: MIT Licence
Keywords: pip,umOpener,opener
Platform: any
